mockcache.py
mockcache3-2.0.dist-info/WHEEL
mockcache3-2.0.dist-info/METADATA
mockcache3-2.0.dist-info/RECORD
